asteca/__init__.py
asteca/cluster.py
asteca/isochrones.py
asteca/likelihood.py
asteca/membership.py
asteca/synthetic.py
asteca/modules/__init__.py
asteca/modules/bayesian_da.py
asteca/modules/cluster_priv.py
asteca/modules/fastmp.py
asteca/modules/imfs.py
asteca/modules/isochrones_priv.py
asteca/modules/likelihood_priv.py
asteca/modules/mass_binary.py
asteca/modules/nmembers.py
asteca/modules/synth_cluster_priv.py
asteca-0.6.1.dist-info/METADATA
asteca-0.6.1.dist-info/WHEEL
asteca-0.6.1.dist-info/licenses/LICENSE.txt
asteca-0.6.1.dist-info/RECORD
