Metadata-Version: 2.4
Name: asteca
Version: 0.6.1
Summary: Stellar cluster analysis package
Author-email: Gabriel I Perren <gabrielperren@gmail.com>
License-Expression: MIT
License-File: LICENSE.txt
Keywords: astrophysics,cluster
Requires-Python: >=3.11.11
Requires-Dist: astropy>=7.0.1
Requires-Dist: fast-histogram>=0.14
Requires-Dist: numpy>=2.0.2
Requires-Dist: scipy>=1.15.2
